<?xml version="1.0" encoding="UTF-8" standalone="yes" ?>
<root>
    <PetSkill id="1300901" type1="1" type2="3" type3="6" cast_type="1" level="1" cast_condition="110" cooldown_time="500" work_time="0" wuxing_cost="0" spirit_cost="0" wuxing_add="0" learn_condition="1" potential_cost="0" learn_prob="10000" learn_step="0" learn_grade="1" learn_rolelvl="1" att1="-1" att2="-1" att3="-1" att4="-1" att5="-1" att6="-1" pet_att="-1" />
	<PetSkill id="1101603" type1="11" type2="0" type3="3" cast_type="0" level="1" cast_condition="255" cooldown_time="0" work_time="0" wuxing_cost="0" spirit_cost="0" wuxing_add="0" learn_condition="1" potential_cost="0" learn_prob="10000" learn_step="0" learn_grade="1" buffid="9999701" learn_rolelvl="1" att1="-1" att2="-1" att3="-1" att4="-1" att5="-1" att6="-1" pet_att="-1" reborn="0" />
	<PetSkill id="1102501" type1="11" type2="0" type3="17" cast_type="0" level="1" cast_condition="255" cooldown_time="0" work_time="0" wuxing_cost="0" spirit_cost="0" wuxing_add="0" learn_condition="1" potential_cost="0" learn_prob="10000" learn_step="0" learn_grade="1" learn_rolelvl="1" att1="-1" att2="-1" att3="-1" att4="-1" att5="-1" att6="-1" pet_att="22" pet_mod="1" reborn="0" />
    <PetSkill id="1102502" type1="11" type2="0" type3="17" cast_type="0" level="2" cast_condition="255" cooldown_time="0" work_time="0" wuxing_cost="0" spirit_cost="0" wuxing_add="0" learn_condition="1" potential_cost="0" learn_prob="10000" learn_step="0" learn_grade="1" learn_rolelvl="1" att1="-1" att2="-1" att3="-1" att4="-1" att5="-1" att6="-1" pet_att="22" pet_mod="2" reborn="0" />
	<PetSkill id="1103001" type1="8" type2="0" type3="6" cast_type="0" level="1" cast_condition="111" cooldown_time="0" work_time="0" wuxing_cost="0" spirit_cost="0" wuxing_add="0" learn_condition="0" potential_cost="10" learn_prob="0" learn_step="0" learn_grade="1" learn_rolelvl="1" att1="8" mod1="109000" att2="12" mod2="21900" att3="14" mod3="21900" att4="136" mod4="2900" att5="49" mod5="50" att6="51" mod6="50" pet_att="-1" reborn="0" />
	<PetSkill id="1103101" type1="8" type2="0" type3="6" cast_type="0" level="1" cast_condition="111" cooldown_time="0" work_time="0" wuxing_cost="0" spirit_cost="0" wuxing_add="0" learn_condition="0" potential_cost="100" learn_prob="0" learn_step="0" learn_grade="1" learn_rolelvl="1" att1="8" mod1="141500" att2="12" mod2="39300" att3="14" mod3="39300" att4="135" mod4="850" att5="88" mod5="200" att6="89" mod6="200" pet_att="-1" reborn="0" />
	<PetSkill id="1103201" type1="8" type2="0" type3="6" cast_type="0" level="1" cast_condition="111" cooldown_time="0" work_time="0" wuxing_cost="0" spirit_cost="0" wuxing_add="0" learn_condition="0" potential_cost="100" learn_prob="0" learn_step="0" learn_grade="1" learn_rolelvl="1" att1="8" mod1="77000" att2="12" mod2="22000" att3="14" mod3="22000" att4="26" mod4="200" att5="44" mod5="100" att6="45" mod6="100" pet_att="-1" reborn="0" />
	<PetSkill id="1103301" type1="8" type2="0" type3="6" cast_type="0" level="1" cast_condition="111" cooldown_time="0" work_time="0" wuxing_cost="0" spirit_cost="0" wuxing_add="0" learn_condition="0" potential_cost="100" learn_prob="0" learn_step="0" learn_grade="1" learn_rolelvl="1" att1="8" mod1="142000" att2="12" mod2="39800" att3="14" mod3="39800" att4="17" mod4="3700" att5="44" mod5="210" att6="45" mod6="210" pet_att="-1" reborn="0" />
	<PetSkill id="1103401" type1="8" type2="0" type3="6" cast_type="0" level="1" cast_condition="111" cooldown_time="0" work_time="0" wuxing_cost="0" spirit_cost="0" wuxing_add="0" learn_condition="0" potential_cost="100" learn_prob="0" learn_step="0" learn_grade="1" learn_rolelvl="1" att1="8" mod1="142500" att2="12" mod2="40300" att3="14" mod3="40300" att4="136" mod4="4000" att5="113" mod5="100" att6="-1" pet_att="-1" reborn="0" />
	<PetSkill id="1103501" type1="8" type2="0" type3="6" cast_type="0" level="1" cast_condition="111" cooldown_time="0" work_time="0" wuxing_cost="0" spirit_cost="0" wuxing_add="0" learn_condition="0" potential_cost="100" learn_prob="0" learn_step="0" learn_grade="1" learn_rolelvl="1" att1="8" mod1="143000" att2="12" mod2="41000" att3="14" mod3="41000" att4="135" mod4="900" att5="28" mod5="1000" att6="-1" pet_att="-1" reborn="0" />
	<PetSkill id="1103601" type1="8" type2="0" type3="6" cast_type="0" level="1" cast_condition="111" cooldown_time="0" work_time="0" wuxing_cost="0" spirit_cost="0" wuxing_add="0" learn_condition="0" potential_cost="100" learn_prob="0" learn_step="0" learn_grade="1" learn_rolelvl="1" att1="8" mod1="143500" att2="12" mod2="41700" att3="14" mod3="41700" att4="17" mod4="3800" att5="135" mod5="900" att6="-1" pet_att="-1" reborn="0" />
	<PetSkill id="1103701" type1="8" type2="0" type3="6" cast_type="0" level="1" cast_condition="111" cooldown_time="0" work_time="0" wuxing_cost="0" spirit_cost="0" wuxing_add="0" learn_condition="0" potential_cost="100" learn_prob="0" learn_step="0" learn_grade="1" learn_rolelvl="1" att1="8" mod1="144000" att2="12" mod2="42200" att3="14" mod3="42200" att4="136" mod4="4200" att5="44" mod5="220" att6="45" mod6="220" pet_att="-1" reborn="0" />
	<PetSkill id="1103801" type1="8" type2="0" type3="6" cast_type="0" level="1" cast_condition="111" cooldown_time="0" work_time="0" wuxing_cost="0" spirit_cost="0" wuxing_add="0" learn_condition="0" potential_cost="100" learn_prob="0" learn_step="0" learn_grade="1" learn_rolelvl="1" att1="8" mod1="144500" att2="12" mod2="42900" att3="14" mod3="42900" att4="16" mod4="3900" att5="135" mod5="950" att6="-1" pet_att="-1" reborn="0" />
	<PetSkill id="1103901" type1="8" type2="0" type3="6" cast_type="0" level="1" cast_condition="111" cooldown_time="0" work_time="0" wuxing_cost="0" spirit_cost="0" wuxing_add="0" learn_condition="0" potential_cost="100" learn_prob="0" learn_step="0" learn_grade="1" learn_rolelvl="1" att1="8" mod1="145000" att2="12" mod2="43400" att3="14" mod3="43400" att4="17" mod4="4000" att5="135" mod5="1000" att6="-1" pet_att="-1" reborn="0" />
	<PetSkill id="1104001" type1="8" type2="0" type3="6" cast_type="0" level="1" cast_condition="111" cooldown_time="0" work_time="0" wuxing_cost="0" spirit_cost="0" wuxing_add="0" learn_condition="0" potential_cost="100" learn_prob="0" learn_step="0" learn_grade="1" learn_rolelvl="1" att1="8" mod1="147000" att2="12" mod2="45800" att3="14" mod3="45800" att4="136" mod4="4200" att5="28" mod5="1000" att6="-1" pet_att="-1" reborn="0" />
	<PetSkill id="1104101" type1="8" type2="0" type3="6" cast_type="0" level="1" cast_condition="111" cooldown_time="0" work_time="0" wuxing_cost="0" spirit_cost="0" wuxing_add="0" learn_condition="0" potential_cost="100" learn_prob="0" learn_step="0" learn_grade="1" learn_rolelvl="1" att1="8" mod1="146000" att2="12" mod2="43900" att3="14" mod3="43900" att4="136" mod4="4300" att5="44" mod5="250" att6="45" mod6="250" pet_att="-1" reborn="0" />
	<PetSkill id="1104201" type1="8" type2="0" type3="6" cast_type="0" level="1" cast_condition="111" cooldown_time="0" work_time="0" wuxing_cost="0" spirit_cost="0" wuxing_add="0" learn_condition="0" potential_cost="100" learn_prob="0" learn_step="0" learn_grade="1" learn_rolelvl="1" att1="8" mod1="147000" att2="12" mod2="44400" att3="14" mod3="44400" att4="135" mod4="1100" att5="28" mod5="1000" att6="-1" pet_att="-1" reborn="0" />
</root>